lstm_reader/__init__.py
lstm_reader/core.py
lstm_reader-0.1.1.dist-info/METADATA
lstm_reader-0.1.1.dist-info/WHEEL
lstm_reader-0.1.1.dist-info/entry_points.txt
lstm_reader-0.1.1.dist-info/top_level.txt
lstm_reader-0.1.1.dist-info/RECORD
